spidur/core.py
spidur/factory.py
spidur/runner.py
spidur-0.2.0.dist-info/LICENSE
spidur-0.2.0.dist-info/METADATA
spidur-0.2.0.dist-info/WHEEL
spidur-0.2.0.dist-info/entry_points.txt
spidur-0.2.0.dist-info/RECORD
