Metadata-Version: 2.1
Name: spidur
Version: 0.2.0
Summary: 🕷️ A lightweight, generic parallel runner for custom scrapers
Home-page: https://github.com/ra0x3/spidur
License: MIT
Keywords: scraping,parallel,async,framework,runner
Author: ra0x3
Author-email: spam.rashad@protonmail.com
Requires-Python: >=3.9,<4.0
Classifier: License :: OSI Approved :: MIT License
Classifier: Programming Language :: Python :: 3
Classifier: Programming Language :: Python :: 3.9
Classifier: Programming Language :: Python :: 3.10
Classifier: Programming Language :: Python :: 3.11
Classifier: Programming Language :: Python :: 3.12
Requires-Dist: pytest (>=8.4.2,<9.0.0)
Requires-Dist: pytest-asyncio (>=1.2.0,<2.0.0)
Project-URL: Repository, https://github.com/ra0x3/spidur
